{
  "id": 11,
  "questions": [
    {
      "text": "I feel a strong pull to put community needs above my personal desires.",
      "direction": "altruism"
    },
    {
      "text": "I tend to protect my personal time fiercely.",
      "direction": "self-focus"
    },
    {
      "text": "I find that I navigate social situations best when the rules are clearly defined.",
      "direction": "hypo-attuned"
    },
    {
      "text": "I find that preparation reduces my anxiety and increases my confidence.",
      "direction": "conscientious"
    },
    {
      "text": "I notice when a text message carries a tone that differs from the sender's usual style.",
      "direction": "hyper-attuned"
    },
    {
      "text": "I feel a strong pull to be in charge of important initiatives.",
      "direction": "agentic"
    },
    {
      "text": "I find that acting in my own interest when I could be helping others feels like a failure.",
      "direction": "altruism"
    },
    {
      "text": "I prefer a general sense of direction over specific, rigid objectives.",
      "direction": "spontaneous"
    },
    {
      "text": "I hold the view that detached, methodical reasoning about painful situations is the approach that yields the broadest view and the most thoughtful response.",
      "direction": "detachment"
    },
    {
      "text": "I often initiate projects without waiting for approval.",
      "direction": "agentic"
    },
    {
      "text": "I prefer to be a contributor alongside others rather than the sole architect.",
      "direction": "yielding"
    },
    {
      "text": "I notice when a group is collectively avoiding a topic that everyone is thinking about.",
      "direction": "hyper-attuned"
    },
    {
      "text": "I believe my nervous system runs at a higher baseline than most people's.",
      "direction": "high-reactive"
    },
    {
      "text": "I find that my emotional state changes gradually, like a thermostat rather than a switch.",
      "direction": "low-reactive"
    },
    {
      "text": "I feel that the obligation to respond to pain is a commitment that defines the core of my ethical life.",
      "direction": "empathy"
    },
    {
      "text": "I believe that the moral weight of someone's suffering should never be discounted simply because responding to it is inconvenient.",
      "direction": "empathy"
    },
    {
      "text": "I find that creating checklists helps me stay focused and avoid overlooking details.",
      "direction": "conscientious"
    },
    {
      "text": "I notice that my face and body betray my emotional intensity before I have a chance to modulate it.",
      "direction": "high-reactive"
    }
  ]
}